sqlazo/__init__.py
sqlazo/sqlazo.py
sqlazo-0.2.0.dist-info/licenses/LICENSE
sqlazo-0.2.0.dist-info/METADATA
sqlazo-0.2.0.dist-info/WHEEL
sqlazo-0.2.0.dist-info/top_level.txt
sqlazo-0.2.0.dist-info/RECORD
