Metadata-Version: 2.4
Name: sqlazo
Version: 0.2.0
Summary: Managing small SQLITE database files
Author-email: Tutos Rive <support@dev2forge.software>
License: MIT License
Project-URL: Homepage, https://docs.dev2forge.software/sqlazo/
Project-URL: Repository, https://github.com/Dev2Forge/sqlazo/
Project-URL: YouTube, https://www.youtube.com/@dev2forge
Classifier: Development Status :: 5 - Production/Stable
Classifier: Intended Audience :: Developers
Classifier: Intended Audience :: Information Technology
Classifier: Intended Audience :: System Administrators
Classifier: Topic :: Software Development :: Libraries
Classifier: Topic :: Software Development :: Debuggers
Classifier: Topic :: System :: Monitoring
Classifier: Topic :: Utilities
Classifier: License :: OSI Approved :: MIT License
Classifier: Programming Language :: Python
Classifier: Programming Language :: Python :: 3.7
Classifier: Programming Language :: Python :: 3.8
Classifier: Programming Language :: Python :: 3.10
Classifier: Programming Language :: Python :: 3.11
Classifier: Programming Language :: Python :: 3.12
Classifier: Programming Language :: Python :: 3.13
Classifier: Programming Language :: Python :: 3.14
Classifier: Operating System :: OS Independent
Classifier: Environment :: Console
Classifier: Environment :: Other Environment
Requires-Python: >=3.7
License-File: LICENSE
Requires-Dist: chromologger<=0.1.10,>=0.1.4
Dynamic: license-file
